zopassport/__init__.py
zopassport/auth.py
zopassport/avatar.py
zopassport/client.py
zopassport/exceptions.py
zopassport/profile.py
zopassport/retry.py
zopassport/session.py
zopassport/storage.py
zopassport/types.py
zopassport/utils.py
zopassport/wallet.py
zopassport-0.1.0.dist-info/METADATA
zopassport-0.1.0.dist-info/WHEEL
zopassport-0.1.0.dist-info/licenses/LICENSE
zopassport-0.1.0.dist-info/RECORD
