Metadata-Version: 2.4
Name: zopassport
Version: 0.1.0
Summary: Zo Passport Python SDK - Phone to Avatar to Passport authentication for Zo World.
Project-URL: Homepage, https://zo.xyz
Project-URL: Repository, https://github.com/ZoHouse/zopassport
Project-URL: Documentation, https://github.com/ZoHouse/zopassport#readme
Project-URL: Issues, https://github.com/ZoHouse/zopassport/issues
Project-URL: Changelog, https://github.com/ZoHouse/zopassport/blob/main/CHANGELOG.md
Author-email: Zo World Team <dev@zo.xyz>
License-File: LICENSE
Keywords: authentication,passport,sdk,web3,zo,zo-world
Classifier: Development Status :: 4 - Beta
Classifier: Intended Audience :: Developers
Classifier: License :: OSI Approved :: MIT License
Classifier: Programming Language :: Python :: 3
Classifier: Programming Language :: Python :: 3.11
Classifier: Topic :: Software Development :: Libraries :: Python Modules
Requires-Python: >=3.11
Requires-Dist: aiofiles>=25.1.0
Requires-Dist: cryptography>=41.0.0
Requires-Dist: httpx>=0.28.1
Requires-Dist: pbkdf2>=1.3
Requires-Dist: pydantic>=2.12.5
Requires-Dist: pytest-asyncio>=1.3.0
Requires-Dist: python-dateutil>=2.8.0
Requires-Dist: tenacity>=8.2.0
Provides-Extra: dev
Requires-Dist: bandit>=1.7.5; extra == 'dev'
Requires-Dist: black>=23.7.0; extra == 'dev'
Requires-Dist: mypy>=1.5.0; extra == 'dev'
Requires-Dist: pre-commit>=3.3.3; extra == 'dev'
Requires-Dist: pytest-asyncio>=0.21.0; extra == 'dev'
Requires-Dist: pytest-cov>=4.1.0; extra == 'dev'
Requires-Dist: pytest-httpx>=0.22.0; extra == 'dev'
Requires-Dist: pytest-mock>=3.11.1; extra == 'dev'
Requires-Dist: pytest>=7.4.0; extra == 'dev'
Requires-Dist: ruff>=0.1.0; extra == 'dev'
Requires-Dist: safety>=2.3.0; extra == 'dev'
Requires-Dist: types-aiofiles>=23.1.0; extra == 'dev'
Requires-Dist: types-python-dateutil>=2.8.19; extra == 'dev'
